snu/__init__.py
snu/snu.py
snu-0.0.1.dist-info/LICENSE
snu-0.0.1.dist-info/WHEEL
snu-0.0.1.dist-info/METADATA
snu-0.0.1.dist-info/RECORD
